adafruit_sht31d.py
adafruit_circuitpython_sht31d-2.3.28.dist-info/licenses/LICENSE
adafruit_circuitpython_sht31d-2.3.28.dist-info/METADATA
adafruit_circuitpython_sht31d-2.3.28.dist-info/WHEEL
adafruit_circuitpython_sht31d-2.3.28.dist-info/top_level.txt
adafruit_circuitpython_sht31d-2.3.28.dist-info/RECORD
