Metadata-Version: 2.4
Name: adafruit-circuitpython-sht31d
Version: 2.3.28
Summary: CircuitPython library for SHT31-D temperature and humidity sensor.
Author-email: Adafruit Industries <circuitpython@adafruit.com>
License: MIT
Project-URL: Homepage, https://github.com/adafruit/Adafruit_CircuitPython_SHT31D
Keywords: adafruit,sht31d,sht31-d,temperature,humidity,sensor,hardware,micropython,circuitpython
Classifier: Intended Audience :: Developers
Classifier: Topic :: Software Development :: Libraries
Classifier: Topic :: Software Development :: Embedded Systems
Classifier: Topic :: System :: Hardware
Classifier: License :: OSI Approved :: MIT License
Classifier: Programming Language :: Python :: 3
License-File: LICENSE
Requires-Dist: Adafruit-Blinka
Requires-Dist: adafruit-circuitpython-busdevice
Requires-Dist: typing-extensions~=4.0
Requires-Dist: adafruit-circuitpython-typing
Dynamic: license-file
